shipyard_s3/__init__.py
shipyard_s3/cli/__init__.py
shipyard_s3/cli/authtest.py
shipyard_s3/cli/download.py
shipyard_s3/cli/move.py
shipyard_s3/cli/remove.py
shipyard_s3/cli/upload.py
shipyard_s3/s3.py
shipyard_s3/utils/exceptions.py
shipyard_s3/utils/utils.py
shipyard_s3-0.2.0.dist-info/METADATA
shipyard_s3-0.2.0.dist-info/WHEEL
shipyard_s3-0.2.0.dist-info/RECORD
